pawnstore/__init__.py
pawnstore/chesscom.py
pawnstore/lichess.py
pawnstore/models.py
pawnstore/services.py
pawnstore-0.2.2.dist-info/METADATA
pawnstore-0.2.2.dist-info/WHEEL
pawnstore-0.2.2.dist-info/top_level.txt
pawnstore-0.2.2.dist-info/RECORD
