Metadata-Version: 2.1
Name: pawnstore
Version: 0.2.2
Summary: Chess library to import your PGN games in a local database
Home-page: https://github.com/KraYmer/pawnstore
Author: Fabrice Laporte
Author-email: kraymer@gmail.com
License: MIT
Keywords: chess
Platform: ALL
Classifier: License :: OSI Approved :: MIT License
Classifier: Programming Language :: Python
Classifier: Environment :: Console
Classifier: Topic :: Games/Entertainment :: Board Games
Requires-Python: >=3.6
Requires-Dist: berserk
Requires-Dist: confuse
Requires-Dist: peewee
Requires-Dist: python-chess
Requires-Dist: requests
Provides-Extra: test
Requires-Dist: coverage >5 ; extra == 'test'
Requires-Dist: pytest >=6 ; extra == 'test'
Requires-Dist: tox >=3 ; extra == 'test'
